txtcn_wiki/__init__.py
txtcn_wiki-0.0.2.data/scripts/txtcn_wiki
txtcn_wiki-0.0.2.dist-info/LICENSE
txtcn_wiki-0.0.2.dist-info/METADATA
txtcn_wiki-0.0.2.dist-info/WHEEL
txtcn_wiki-0.0.2.dist-info/top_level.txt
txtcn_wiki-0.0.2.dist-info/zip-safe
txtcn_wiki-0.0.2.dist-info/RECORD
