Metadata-Version: 2.1
Name: txtcn-wiki
Version: 0.0.2
Summary: 从维基百科抽取中文语料
Home-page: https://github.com/txtcn/wiki
Author: 张沈鹏
Author-email: zsp042@gmail.com
License: UNKNOWN
Platform: UNKNOWN
Requires-Dist: zd
Requires-Dist: tqdm
Requires-Dist: gensim
Requires-Dist: opencc
Requires-Dist: fire
